{ 
    "primary":[
        {
            "color":"#D50000",
            "name":"vermelho",
            "audio":"vermelho"
        },
        {
            "color":"#2979FF",
            "name":"azul",
            "audio":"azul"
        },{
            "color":"#FFEA00",
            "name":"amarelo",
            "audio":"amarelo"
        }
    ],
    "initial":[
        {
            "color":"#D50000",
            "name":"vermelho",
            "audio":"vermelho"
        },{
            "color":"#C2185B",
            "name":"rosa",
            "audio":"rosa"
        },{
            "color":"#AA00FF",
            "name":"roxo",
            "audio":"rôxo"
        },{
            "color":"#2962FF",
            "name":"azul",
            "audio":"azul"
        },{
            "color":"#00C853",
            "name":"verde",
            "audio":"verde"
        },{
            "color":"#FFD600",
            "name":"amarelo",
            "audio":"amarelo"
        },{
            "color":"#FF6D00",
            "name":"laranja",
            "audio":"laranja"
        },{
            "color":"#5D4037",
            "name":"marrom",
            "audio":"marrom"
        },{
            "color":"#616161",
            "name":"cinza",
            "audio":"cinza"
        },{
            "color":"#000000",
            "name":"preto",
            "audio":"preto"
        },{
            "color":"#FFFFFF",
            "name":"branco",
            "audio":"branco"
        }
    ],
    "advanced":[
        {
            "color":"#FFFFFF",
            "name":"avancado",
            "audio":"PUTA Q PARIUUU"
        }
    ]

}